base_telegram_bot/__init__.py
base_telegram_bot/py.typed
base_telegram_bot-0.0.2.dist-info/LICENSE
base_telegram_bot-0.0.2.dist-info/WHEEL
base_telegram_bot-0.0.2.dist-info/METADATA
base_telegram_bot-0.0.2.dist-info/RECORD
